{
    "description": "关卡选择界面布局 - 锯齿蛇形路径, 3行5列, 12关",
    "grid": {
        "rows": 3,
        "cols": 5,
        "nodeSize": 52,
        "gap": 20
    },
    "path": [
        { "row": 1, "col": 1, "comment": "关卡1: 起点(左上)" },
        { "row": 1, "col": 2, "comment": "关卡2: 右" },
        { "row": 2, "col": 2, "comment": "关卡3: 下" },
        { "row": 2, "col": 3, "comment": "关卡4: 右" },
        { "row": 1, "col": 3, "comment": "关卡5: 上" },
        { "row": 1, "col": 4, "comment": "关卡6: 右" },
        { "row": 2, "col": 4, "comment": "关卡7: 下" },
        { "row": 2, "col": 5, "comment": "关卡8: 右" },
        { "row": 3, "col": 5, "comment": "关卡9: 下" },
        { "row": 3, "col": 4, "comment": "关卡10: 左" },
        { "row": 3, "col": 3, "comment": "关卡11: 左" },
        { "row": 3, "col": 2, "comment": "关卡12: 左(终点)" }
    ],
    "style": {
        "unlocked": {
            "backgroundColor": [180, 40, 50, 255],
            "borderColor": [0, 0, 0, 255],
            "textColor": [255, 255, 255, 255]
        },
        "locked": {
            "backgroundColor": [0, 0, 0, 0],
            "borderColor": [255, 255, 255, 150],
            "borderStyle": "dashed",
            "icon": "🔒"
        },
        "connection": {
            "color": [255, 255, 255, 200],
            "thickness": 3
        }
    }
}
